vibephysics/__init__.py
vibephysics/annotation/__init__.py
vibephysics/annotation/base.py
vibephysics/annotation/bbox.py
vibephysics/annotation/manager.py
vibephysics/annotation/motion_trail.py
vibephysics/annotation/point_tracking.py
vibephysics/camera/__init__.py
vibephysics/camera/base.py
vibephysics/camera/center.py
vibephysics/camera/following.py
vibephysics/camera/manager.py
vibephysics/camera/mounted.py
vibephysics/foundation/README.md
vibephysics/foundation/__init__.py
vibephysics/foundation/go2.py
vibephysics/foundation/ground.py
vibephysics/foundation/lighting.py
vibephysics/foundation/materials.py
vibephysics/foundation/objects.py
vibephysics/foundation/open_duck.py
vibephysics/foundation/physics.py
vibephysics/foundation/robot.py
vibephysics/foundation/trajectory.py
vibephysics/foundation/water.py
vibephysics/mapping/__init__.py
vibephysics/mapping/colmap.py
vibephysics/mapping/glomap.py
vibephysics/mapping/map_visual.py
vibephysics/mapping/pipeline.py
vibephysics/mapping/utils.py
vibephysics/setup/__init__.py
vibephysics/setup/exporter.py
vibephysics/setup/gsplat.py
vibephysics/setup/importer.py
vibephysics/setup/scene.py
vibephysics/setup/viewport.py
vibephysics-0.2.4.dist-info/METADATA
vibephysics-0.2.4.dist-info/WHEEL
vibephysics-0.2.4.dist-info/entry_points.txt
vibephysics-0.2.4.dist-info/top_level.txt
vibephysics-0.2.4.dist-info/RECORD
