Metadata-Version: 2.4
Name: vibephysics
Version: 0.2.4
Summary: Physics simulation and annotation tools for Blender
Author-email: tsunyi <tsunyi@mimiaigen.com>
Project-URL: Homepage, https://github.com/yourusername/vibephysics
Project-URL: Documentation, https://github.com/yourusername/vibephysics#readme
Project-URL: Repository, https://github.com/yourusername/vibephysics.git
Project-URL: Issues, https://github.com/yourusername/vibephysics/issues
Keywords: blender,physics,simulation,annotation,rigid-body,water,robotics
Classifier: Development Status :: 3 - Alpha
Classifier: Intended Audience :: Developers
Classifier: Intended Audience :: Science/Research
Classifier: Operating System :: OS Independent
Classifier: Programming Language :: Python :: 3
Classifier: Programming Language :: Python :: 3.11
Classifier: Topic :: Multimedia :: Graphics :: 3D Modeling
Classifier: Topic :: Scientific/Engineering :: Visualization
Requires-Python: >=3.11
Requires-Dist: tqdm>=4.0
Requires-Dist: numpy<2.0
Requires-Dist: bpy>=5.0
Requires-Dist: pycolmap
Provides-Extra: dev
Requires-Dist: pytest>=7.0; extra == "dev"
Requires-Dist: black; extra == "dev"
Requires-Dist: ruff; extra == "dev"
